hctest_basic_platform/__init__.py
hctest_basic_platform/app.py
hctest_basic_platform/fontview.py
hctest_basic_platform/main.py
hctest_basic_platform/run.py
hctest_basic_platform/sql_manage.py
hctest_basic_platform/test_execute.py
hctest_basic_platform/layui/layui.css
hctest_basic_platform/layui/layui.js
hctest_basic_platform/templates/addTestCase.html
hctest_basic_platform/templates/caseList.html
hctest_basic_platform/templates/index.html
hctest_basic_platform/templates/test.html
hctest_basic_platform/templates/updateTestCase.html
hctest_basic_platform-6.0.dist-info/METADATA
hctest_basic_platform-6.0.dist-info/WHEEL
hctest_basic_platform-6.0.dist-info/top_level.txt
hctest_basic_platform-6.0.dist-info/RECORD
