Metadata-Version: 2.1
Name: hctest-basic-platform
Version: 6.0
Summary: 初级平台
Home-page: https://github.com/pypa/sampleproject
Author: cf
Author-email: dingjun_baby@yeah.net
License: UNKNOWN
Platform: UNKNOWN
Classifier: Programming Language :: Python :: 3
Classifier: License :: OSI Approved :: MIT License
Classifier: Operating System :: OS Independent
Requires-Python: >=3.6
Requires-Dist: Flask
Requires-Dist: Flask-Cors
Requires-Dist: PyMySQL
Requires-Dist: pytest
Requires-Dist: requests
Requires-Dist: allure-pytest
